{
    "type": "pipelines",
    "parent": "",
    "resources": [
        {
            "resourceType": "adgroups",
            "resources": [
                {
                    "type": "developers"
                }
            ]
        },
        {
            "resourceType": "storageaccounts",
            "resources": [
                {
                    "type": "diagnostics"
                },
                {
                    "type": "adlsv2storage"
                },
                {
                    "type": "storage"
                }
            ]
        },
        {
            "resourceType": "keyvaultsecrets",
            "resources": [
                {
                    "type": "storageconnectionstring"
                }
            ]
        },
        {
            "resourceType": "adfs",
            "resources": [
                {
                    "type": "adf"
                }
            ]
        },
        {
            "resourceType": "diagnostics",
            "resources": [
                {
                    "type": "appkeyvault"
                },
                {
                    "type": "adf"
                }
            ]
        }
    ]
}